{
  "topics": [
    {
      "id": "boat",
      "title": "Boat & Sailing",
      "icon": "⛵",
      "count": 57,
      "updatedAt": "2026-05-01"
    },
    {
      "id": "hiking",
      "title": "Hiking",
      "icon": "🥾",
      "count": 105,
      "updatedAt": "2026-05-04"
    },
    {
      "id": "symbols",
      "title": "Symbols & Notation",
      "icon": "⌨️",
      "count": 103,
      "updatedAt": "2026-05-05"
    },
    {
      "id": "car-accident",
      "title": "Car Accident & Insurance",
      "icon": "🚗",
      "count": 144,
      "updatedAt": "2026-05-14"
    },
    {
      "id": "confusables",
      "title": "Easily Confused Words",
      "icon": "🔀",
      "count": 310,
      "updatedAt": "2026-05-14"
    },
    {
      "id": "cooking",
      "title": "Cooking",
      "icon": "🍳",
      "count": 107,
      "updatedAt": "2026-05-20"
    }
  ]
}
